Facad1ng/__init__.py
Facad1ng/main.py
Facad1ng-1.0.1.dist-info/METADATA
Facad1ng-1.0.1.dist-info/WHEEL
Facad1ng-1.0.1.dist-info/entry_points.txt
Facad1ng-1.0.1.dist-info/top_level.txt
Facad1ng-1.0.1.dist-info/RECORD
