Metadata-Version: 2.2
Name: Facad1ng
Version: 1.0.1
Summary: The Ultimate URL Masking Tool
Home-page: https://github.com/spyboy-productions/Facad1ng
Author: Spyboy
Author-email: contact@spyboy.in
License: MIT
Keywords: masking,phishing,url-shortener,mask-phishing-url,hide-phishing-link,url-phishing
Classifier: Development Status :: 1 - Planning
Classifier: Intended Audience :: Developers
Classifier: Programming Language :: Python :: 3
Classifier: Operating System :: Unix
Classifier: Operating System :: MacOS :: MacOS X
Classifier: Operating System :: Microsoft :: Windows
Requires-Dist: pyshorteners
Dynamic: author
Dynamic: author-email
Dynamic: classifier
Dynamic: description
Dynamic: description-content-type
Dynamic: home-page
Dynamic: keywords
Dynamic: license
Dynamic: requires-dist
Dynamic: summary
